representation/__init__.py
representation/api.py
representation/representation.py
representation/interfaces/__init__.py
representation/interfaces/http.py
representation-1.0.3.dist-info/METADATA
representation-1.0.3.dist-info/WHEEL
representation-1.0.3.dist-info/top_level.txt
representation-1.0.3.dist-info/RECORD
